{
"meta":{"test_sets":[],"test_metrics":[],"learn_metrics":[{"best_value":"Min","name":"Logloss"}],"launch_mode":"Train","parameters":"","iteration_count":100,"learn_sets":["learn"],"name":"experiment"},
"iterations":[
{"learn":[0.6661054293],"iteration":0,"passed_time":0.05906835153,"remaining_time":5.847766802},
{"learn":[0.641020847],"iteration":1,"passed_time":0.05949110337,"remaining_time":2.915064065},
{"learn":[0.6214852872],"iteration":2,"passed_time":0.05972595624,"remaining_time":1.931139252},
{"learn":[0.6000212473],"iteration":3,"passed_time":0.05994910188,"remaining_time":1.438778445},
{"learn":[0.5781497556],"iteration":4,"passed_time":0.06017174757,"remaining_time":1.143263204},
{"learn":[0.5639325839],"iteration":5,"passed_time":0.06039089359,"remaining_time":0.9461239996},
{"learn":[0.5476272045],"iteration":6,"passed_time":0.0606739086,"remaining_time":0.8060962142},
{"learn":[0.534184874],"iteration":7,"passed_time":0.06219134896,"remaining_time":0.7152005131},
{"learn":[0.5178521566],"iteration":8,"passed_time":0.06296244298,"remaining_time":0.6366202568},
{"learn":[0.506183696],"iteration":9,"passed_time":0.06320754489,"remaining_time":0.568867904},
{"learn":[0.4964747287],"iteration":10,"passed_time":0.0634228996,"remaining_time":0.5131489149},
{"learn":[0.4867645288],"iteration":11,"passed_time":0.06366770987,"remaining_time":0.466896539},
{"learn":[0.4771872965],"iteration":12,"passed_time":0.06389573005,"remaining_time":0.4276098857},
{"learn":[0.4665607888],"iteration":13,"passed_time":0.06412087551,"remaining_time":0.3938853781},
{"learn":[0.4545599102],"iteration":14,"passed_time":0.06441993066,"remaining_time":0.3650462738},
{"learn":[0.4458395865],"iteration":15,"passed_time":0.06464657598,"remaining_time":0.3393945239},
{"learn":[0.4373313388],"iteration":16,"passed_time":0.06486543036,"remaining_time":0.3166959247},
{"learn":[0.428046736],"iteration":17,"passed_time":0.06508303486,"remaining_time":0.296489381},
{"learn":[0.4206519632],"iteration":18,"passed_time":0.065304389,"remaining_time":0.2784029215},
{"learn":[0.4128737718],"iteration":19,"passed_time":0.06553640881,"remaining_time":0.2621456352},
{"learn":[0.4042804887],"iteration":20,"passed_time":0.06576547056,"remaining_time":0.2474034369},
{"learn":[0.3974584341],"iteration":21,"passed_time":0.06601973827,"remaining_time":0.2340699811},
{"learn":[0.3913337491],"iteration":22,"passed_time":0.06625284131,"remaining_time":0.2218029905},
{"learn":[0.3864712207],"iteration":23,"passed_time":0.06675629388,"remaining_time":0.2113949306},
{"learn":[0.3794724011],"iteration":24,"passed_time":0.06723745688,"remaining_time":0.2017123706},
{"learn":[0.3756557289],"iteration":25,"passed_time":0.06757530005,"remaining_time":0.1923297001},
{"learn":[0.3715111423],"iteration":26,"passed_time":0.06779427942,"remaining_time":0.1832956443},
{"learn":[0.3672517172],"iteration":27,"passed_time":0.06801292548,"remaining_time":0.1748903798},
{"learn":[0.3626796117],"iteration":28,"passed_time":0.06840847155,"remaining_time":0.1674828097},
{"learn":[0.3567532138],"iteration":29,"passed_time":0.06873960702,"remaining_time":0.1603924164},
{"learn":[0.3520113778],"iteration":30,"passed_time":0.06895712819,"remaining_time":0.1534852208},
{"learn":[0.3487780254],"iteration":31,"passed_time":0.06918010718,"remaining_time":0.1470077278},
{"learn":[0.3448989115],"iteration":32,"passed_time":0.06941383516,"remaining_time":0.1409311199},
{"learn":[0.3405587227],"iteration":33,"passed_time":0.06962319044,"remaining_time":0.1351508991},
{"learn":[0.3362021041],"iteration":34,"passed_time":0.069847211,"remaining_time":0.129716249},
{"learn":[0.3329791106],"iteration":35,"passed_time":0.07006556543,"remaining_time":0.1245610052},
{"learn":[0.3292688812],"iteration":36,"passed_time":0.07028371154,"remaining_time":0.1196722656},
{"learn":[0.326779997],"iteration":37,"passed_time":0.07050256592,"remaining_time":0.1150305023},
{"learn":[0.3220025849],"iteration":38,"passed_time":0.07139652336,"remaining_time":0.1116714853},
{"learn":[0.3194857627],"iteration":39,"passed_time":0.07185802155,"remaining_time":0.1077870323},
{"learn":[0.3159411731],"iteration":40,"passed_time":0.07214532781,"remaining_time":0.1038188864},
{"learn":[0.3125935471],"iteration":41,"passed_time":0.07236972334,"remaining_time":0.09993914175},
{"learn":[0.3099691797],"iteration":42,"passed_time":0.07251125167,"remaining_time":0.09611956617},
{"learn":[0.3062811507],"iteration":43,"passed_time":0.0735454459,"remaining_time":0.09360329478},
{"learn":[0.3032800567],"iteration":44,"passed_time":0.07376838323,"remaining_time":0.09016135728},
{"learn":[0.3005573961],"iteration":45,"passed_time":0.07398902911,"remaining_time":0.08685668635},
{"learn":[0.296790726],"iteration":46,"passed_time":0.07423854727,"remaining_time":0.08371580862},
{"learn":[0.2933453505],"iteration":47,"passed_time":0.07446419268,"remaining_time":0.08066954207},
{"learn":[0.2904934556],"iteration":48,"passed_time":0.07468038064,"remaining_time":0.07772855944},
{"learn":[0.2872340317],"iteration":49,"passed_time":0.0749026097,"remaining_time":0.0749026097},
{"learn":[0.2844418562],"iteration":50,"passed_time":0.07512338057,"remaining_time":0.07217736565},
{"learn":[0.2812804206],"iteration":51,"passed_time":0.07534544298,"remaining_time":0.06954963968},
{"learn":[0.2784407108],"iteration":52,"passed_time":0.0755649223,"remaining_time":0.0670104028},
{"learn":[0.2754618688],"iteration":53,"passed_time":0.075936054,"remaining_time":0.06468626823},
{"learn":[0.2729788801],"iteration":54,"passed_time":0.07643729845,"remaining_time":0.06253960782},
{"learn":[0.2709813164],"iteration":55,"passed_time":0.07689204727,"remaining_time":0.06041518},
{"learn":[0.2689588798],"iteration":56,"passed_time":0.07733242244,"remaining_time":0.05833849412},
{"learn":[0.2663120351],"iteration":57,"passed_time":0.07782300122,"remaining_time":0.05635458709},
{"learn":[0.2638863288],"iteration":58,"passed_time":0.07841544541,"remaining_time":0.05449208918},
{"learn":[0.2612334774],"iteration":59,"passed_time":0.07890702409,"remaining_time":0.05260468273},
{"learn":[0.2585385475],"iteration":60,"passed_time":0.07936027306,"remaining_time":0.05073853523},
{"learn":[0.255809828],"iteration":61,"passed_time":0.07987035,"remaining_time":0.04895279516},
{"learn":[0.2529750126],"iteration":62,"passed_time":0.08097299611,"remaining_time":0.04755556915},
{"learn":[0.2501333888],"iteration":63,"passed_time":0.08149615516,"remaining_time":0.04584158728},
{"learn":[0.2469937091],"iteration":64,"passed_time":0.08199260838,"remaining_time":0.04414986605},
{"learn":[0.2443903104],"iteration":65,"passed_time":0.08257638672,"remaining_time":0.04253935073},
{"learn":[0.2419267502],"iteration":66,"passed_time":0.08294660184,"remaining_time":0.04085429643},
{"learn":[0.2396492937],"iteration":67,"passed_time":0.08317233057,"remaining_time":0.03913992027},
{"learn":[0.237290761],"iteration":68,"passed_time":0.08339701773,"remaining_time":0.03746822536},
{"learn":[0.2355425177],"iteration":69,"passed_time":0.08361695535,"remaining_time":0.03583583801},
{"learn":[0.2332757253],"iteration":70,"passed_time":0.08383439319,"remaining_time":0.03424221694},
{"learn":[0.2315951177],"iteration":71,"passed_time":0.08443466997,"remaining_time":0.03283570499},
{"learn":[0.2293280785],"iteration":72,"passed_time":0.0849515796,"remaining_time":0.03142044725},
{"learn":[0.2276544317],"iteration":73,"passed_time":0.08548157134,"remaining_time":0.03003406561},
{"learn":[0.225678827],"iteration":74,"passed_time":0.08597664969,"remaining_time":0.02865888323},
{"learn":[0.2236690575],"iteration":75,"passed_time":0.08665300264,"remaining_time":0.0273641061},
{"learn":[0.2224467038],"iteration":76,"passed_time":0.08696818128,"remaining_time":0.02597750869},
{"learn":[0.2207510836],"iteration":77,"passed_time":0.08719507657,"remaining_time":0.02459348313},
{"learn":[0.2196251951],"iteration":78,"passed_time":0.08742872122,"remaining_time":0.02324054615},
{"learn":[0.2176021753],"iteration":79,"passed_time":0.08765095028,"remaining_time":0.02191273757},
{"learn":[0.2159348683],"iteration":80,"passed_time":0.08786684661,"remaining_time":0.0206107418},
{"learn":[0.2143262993],"iteration":81,"passed_time":0.08808928398,"remaining_time":0.01933667209},
{"learn":[0.2127073148],"iteration":82,"passed_time":0.08830393043,"remaining_time":0.0180863472},
{"learn":[0.2100997768],"iteration":83,"passed_time":0.08853203394,"remaining_time":0.01686324456},
{"learn":[0.2088719028],"iteration":84,"passed_time":0.08874913848,"remaining_time":0.01566161267},
{"learn":[0.2070604101],"iteration":85,"passed_time":0.08896724293,"remaining_time":0.01448303955},
{"learn":[0.205017631],"iteration":86,"passed_time":0.08919188844,"remaining_time":0.01332752356},
{"learn":[0.2032864184],"iteration":87,"passed_time":0.08940995122,"remaining_time":0.01219226608},
{"learn":[0.2018828975],"iteration":88,"passed_time":0.08962284783,"remaining_time":0.01107698119},
{"learn":[0.2005533035],"iteration":89,"passed_time":0.08985265951,"remaining_time":0.009983628835},
{"learn":[0.1991665282],"iteration":90,"passed_time":0.09007538853,"remaining_time":0.00890855491},
{"learn":[0.1969771671],"iteration":91,"passed_time":0.09029670101,"remaining_time":0.007851887045},
{"learn":[0.1959962418],"iteration":92,"passed_time":0.09051676361,"remaining_time":0.006813089734},
{"learn":[0.1943162016],"iteration":93,"passed_time":0.09073461809,"remaining_time":0.005791571367},
{"learn":[0.1931233841],"iteration":94,"passed_time":0.09095093104,"remaining_time":0.004786891107},
{"learn":[0.1924910795],"iteration":95,"passed_time":0.09117270181,"remaining_time":0.003798862576},
{"learn":[0.191382329],"iteration":96,"passed_time":0.09139759729,"remaining_time":0.002826729813},
{"learn":[0.1892133112],"iteration":97,"passed_time":0.09161391024,"remaining_time":0.001869671638},
{"learn":[0.188540429],"iteration":98,"passed_time":0.09182447374,"remaining_time":0.0009275199368},
{"learn":[0.1875721433],"iteration":99,"passed_time":0.09204266152,"remaining_time":0}
]}